{
  "100": {
    "Australia": 79,
    "England": 179
  },
  "130": {
    "India": 144,
    "Zimbabwe": 140
  },
  "132": {
    "England": 191,
    "New Zealand": 135
  },
  "173": {
    "Australia": 157,
    "India": 184
  },
  "188": {
    "Australia": 171,
    "India": 140
  },
  "213": {
    "Pakistan": 137,
    "West Indies": 138
  },
  "216": {
    "England": 128,
    "West Indies": 125
  },
  "220": {
    "England": 185,
    "Pakistan": 137
  },
  "222": {
    "India": 244,
    "West Indies": 245
  },
  "235": {
    "Australia": 166,
    "India": 167
  },
  "248": {
    "England": 136,
    "Sri Lanka": 137
  },
  "268": {
    "Pakistan": 132,
    "Sri Lanka": 133
  },
  "27": {
    "England": 136,
    "Pakistan": 144
  },
  "275": {
    "England": 151,
    "Pakistan": 147
  },
  "276": {
    "India": 211,
    "Sri Lanka": 206
  },
  "285": {
    "England": 161,
    "Sri Lanka": 163
  },
  "310": {
    "India": 199,
    "South Africa": 200
  },
  "335": {
    "Bangladesh": 85,
    "Pakistan": 135
  },
  "336": {
    "India": 131,
    "Pakistan": 130
  },
  "343": {
    "New Zealand": 171,
    "Pakistan": 168
  },
  "346": {
    "Australia": 160,
    "India": 161
  },
  "367": {
    "India": 157,
    "Pakistan": 152
  },
  "374": {
    "India": 142,
    "Sri Lanka": 138
  },
  "377": {
    "England": 161,
    "West Indies": 82
  },
  "381": {
    "New Zealand": 155,
    "Pakistan": 171
  },
  "410": {
    "England": 181,
    "India": 177
  },
  "419": {
    "England": 129,
    "Pakistan": 126
  },
  "433": {
    "England": 149,
    "New Zealand": 148
  },
  "452": {
    "Pakistan": 158,
    "West Indies": 152
  },
  "456": {
    "England": 193,
    "West Indies": 208
  },
  "460": {
    "Pakistan": 174,
    "Sri Lanka": 172
  },
  "481": {
    "England": 230,
    "South Africa": 229
  },
  "497": {
    "Australia": 151,
    "India": 188
  },
  "506": {
    "Pakistan": 116,
    "West Indies": 115
  },
  "509": {
    "Pakistan": 119,
    "South Africa": 120
  },
  "51": {
    "Australia": 97,
    "Pakistan": 96
  },
  "514": {
    "England": 29,
    "South Africa": 77
  },
  "519": {
    "India": 79,
    "New Zealand": 126
  },
  "523": {
    "Bangladesh": 101,
    "Pakistan": 203
  },
  "528": {
    "England": 88,
    "West Indies": 113
  },
  "529": {
    "Afghanistan": 80,
    "England": 196
  },
  "53": {
    "India": 163,
    "Sri Lanka": 167
  },
  "540": {
    "England": 214,
    "New Zealand": 174
  },
  "550": {
    "New Zealand": 80,
    "Pakistan": 183
  },
  "75": {
    "England": 118,
    "South Africa": 119
  },
  "77": {
    "Australia": 131,
    "England": 130
  },
  "85": {
    "India": 112,
    "Zimbabwe": 111
  },
  "91": {
    "India": 103,
    "Zimbabwe": 99
  },
  "96": {
    "Pakistan": 122,
    "Sri Lanka": 99
  }
}